Metadata-Version: 2.1
Name: CrawlUpDetec
Version: 1.0.2
Summary: a package help detect website update or not
Author: Frank
Requires-Python: >=3.8
License-File: LICENSE
